mc_check.py
mc_check-1.0.6.dist-info/LICENSE
mc_check-1.0.6.dist-info/METADATA
mc_check-1.0.6.dist-info/WHEEL
mc_check-1.0.6.dist-info/entry_points.txt
mc_check-1.0.6.dist-info/top_level.txt
mc_check-1.0.6.dist-info/RECORD
